<?xml version="1.0" encoding="utf-8" ?><Defs><IncidentDef><defName>Milira_FallenAngel_Drop</defName><label>折翼天使</label><category>Misc</category><targetTags><li>Map_PlayerHome</li></targetTags><workerClass>Milira.IncidentWorker_GiveQuestExceptMiliraScenario</workerClass><questScriptDef>Milira_FallenAngel_Drop</questScriptDef><baseChance>0</baseChance><requireColonistsPresent>True</requireColonistsPresent></IncidentDef><IncidentDef><defName>Milira_FallenAngel_Return</defName><label>米莉拉加入</label><category>Misc</category><targetTags><li>Map_PlayerHome</li></targetTags><workerClass>Milira.IncidentWorker_GiveQuestExceptMiliraScenario</workerClass><questScriptDef>Milira_FallenAngel_Return</questScriptDef><baseChance>0</baseChance></IncidentDef><IncidentDef><defName>Milira_FallenAngel_ToChurch</defName><label>教会接洽</label><category>Misc</category><targetTags><li>Map_PlayerHome</li></targetTags><workerClass>Milira.IncidentWorker_GiveQuestExceptMiliraScenario</workerClass><questScriptDef>Milira_FallenAngel_ToChurch</questScriptDef><baseChance>0</baseChance></IncidentDef></Defs>